sugarplum/__about__.py
sugarplum/__init__.py
sugarplum-0.8.dist-info/METADATA
sugarplum-0.8.dist-info/WHEEL
sugarplum-0.8.dist-info/licenses/LICENSE.txt
sugarplum-0.8.dist-info/RECORD
