Metadata-Version: 2.4
Name: sugarplum
Version: 0.8
Summary: A library to manage inputs for Advent of Code puzzles
Project-URL: Documentation, https://github.com/stephenlutes/sugarplum#readme
Project-URL: Issues, https://github.com/stephenlutes/sugarplum/issues
Project-URL: Source, https://github.com/stephenlutes/sugarplum
Author: Stephen Lutes
License-Expression: MIT
License-File: LICENSE.txt
Classifier: Development Status :: 4 - Beta
Classifier: Programming Language :: Python
Classifier: Programming Language :: Python :: 3.9
Classifier: Programming Language :: Python :: 3.10
Classifier: Programming Language :: Python :: 3.11
Classifier: Programming Language :: Python :: 3.12
Classifier: Programming Language :: Python :: 3.13
Classifier: Programming Language :: Python :: Implementation :: CPython
Classifier: Programming Language :: Python :: Implementation :: PyPy
Requires-Python: >=3.9
Requires-Dist: pyyaml
